motorrijtuigenbelasting/__init__.py
motorrijtuigenbelasting/vehicles/__init__.py
motorrijtuigenbelasting/vehicles/car.py
motorrijtuigenbelasting/vehicles/constants.py
motorrijtuigenbelasting/vehicles/motorcycle.py
tests/__init__.py
tests/test_car.py
tests/test_motorcycle.py
tests/test_vehicle.py
motorrijtuigenbelasting-0.1.0.dist-info/LICENSE
motorrijtuigenbelasting-0.1.0.dist-info/METADATA
motorrijtuigenbelasting-0.1.0.dist-info/WHEEL
motorrijtuigenbelasting-0.1.0.dist-info/top_level.txt
motorrijtuigenbelasting-0.1.0.dist-info/RECORD
