Metadata-Version: 2.1
Name: motorrijtuigenbelasting
Version: 0.1.0
Summary: Calculate Dutch road tax Motorrijtuigenbelasting(MRB) for vehicles.
Home-page: https://github.com/VitoMinheere/motorrijtuigenbelasting
Author: Vito Minheere
Author-email: vito@vipyr.nl
Classifier: Programming Language :: Python :: 3
Classifier: License :: OSI Approved :: MIT License
Classifier: Operating System :: OS Independent
Requires-Python: >=3.7
License-File: LICENSE
